{
  "visual": {
    "name": "RingChart",
    "displayName": "RingChart",
    "guid": "RingChart1445472000809",
    "visualClassName": "RingChart",
    "version": "2.0.1",
    "description": "RingChart is a multilevel donut chart, used to visualize hierarchical data, depicted by concentric circles.",
    "supportUrl": "https://community.powerbi.com"
  },
  "apiVersion": "2.5.0",
  "author": {
    "name": "Microsoft",
    "email": "pbicvsupport@microsoft.com"
  },
  "assets": {
    "icon": "assets/icon.png"
  },
  "externalJS": [
    "node_modules/globalize/lib/globalize.js",
    "node_modules/globalize/lib/cultures/globalize.cultures.js"
  ],
  "capabilities": "capabilities.json"
}
